smsgateway/__init__.py
smsgateway/admin.py
smsgateway/enums.py
smsgateway/factories.py
smsgateway/models.py
smsgateway/sms.py
smsgateway/tasks.py
smsgateway/urls.py
smsgateway/utils.py
smsgateway/views.py
smsgateway/__pycache__/__init__.cpython-37.pyc
smsgateway/__pycache__/enums.cpython-37.pyc
smsgateway/__pycache__/models.cpython-37.pyc
smsgateway/__pycache__/sms.cpython-37.pyc
smsgateway/__pycache__/utils.cpython-37.pyc
smsgateway/backends/__init__.py
smsgateway/backends/base.py
smsgateway/backends/file.py
smsgateway/backends/jasmin.py
smsgateway/backends/kpnbe.py
smsgateway/backends/mobileweb.py
smsgateway/backends/redistore.py
smsgateway/backends/smpp.py
smsgateway/backends/smsextrapro.py
smsgateway/backends/spryng.py
smsgateway/backends/__pycache__/__init__.cpython-37.pyc
smsgateway/backends/__pycache__/base.cpython-37.pyc
smsgateway/backends/__pycache__/redistore.cpython-37.pyc
smsgateway/backends/__pycache__/smpp.cpython-37.pyc
smsgateway/locale/fr/LC_MESSAGES/django.mo
smsgateway/locale/fr/LC_MESSAGES/django.po
smsgateway/locale/nl/LC_MESSAGES/django.mo
smsgateway/locale/nl/LC_MESSAGES/django.po
smsgateway/management/__init__.py
smsgateway/management/__pycache__/__init__.cpython-37.pyc
smsgateway/management/commands/__init__.py
smsgateway/management/commands/recv_smses.py
smsgateway/management/commands/send_smses.py
smsgateway/migrations/0001_initial.py
smsgateway/migrations/0002_auto_20170116_1117.py
smsgateway/migrations/0003_auto_20171012_1427.py
smsgateway/migrations/0004_auto_20190117_1802.py
smsgateway/migrations/__init__.py
smsgateway/migrations/__pycache__/0001_initial.cpython-37.pyc
smsgateway/migrations/__pycache__/0002_auto_20170116_1117.cpython-37.pyc
smsgateway/migrations/__pycache__/0003_auto_20171012_1427.cpython-37.pyc
smsgateway/migrations/__pycache__/0004_auto_20190117_1802.cpython-37.pyc
smsgateway/migrations/__pycache__/__init__.cpython-37.pyc
smsgateway/smpplib/__init__.py
smsgateway/smpplib/client.py
smsgateway/smpplib/command.py
django_smsgateway-2.1.20.dist-info/LICENSE.txt
django_smsgateway-2.1.20.dist-info/METADATA
django_smsgateway-2.1.20.dist-info/WHEEL
django_smsgateway-2.1.20.dist-info/top_level.txt
django_smsgateway-2.1.20.dist-info/RECORD
