Metadata-Version: 2.1
Name: django-smsgateway
Version: 2.1.20
Summary: SMS gateway for sending text messages
Home-page: https://github.com/vikingco/smsgateway
Author: Unleashed NV
Author-email: operations@unleashed.be
License: BSD
Platform: UNKNOWN
Classifier: Intended Audience :: Developers
Classifier: Programming Language :: Python
Classifier: Operating System :: OS Independent
Classifier: Environment :: Web Environment
Classifier: Framework :: Django
Requires-Dist: Django (>=2.1.5)
Requires-Dist: django-statsd-unleashed (>=1.0.1)
Requires-Dist: statsd (>=2.1.2)
Requires-Dist: redis (>=2.10.5)
Requires-Dist: celery (==4.0.2)
Requires-Dist: kombu (==4.0.2)
Requires-Dist: billiard (==3.5.0.2)
Requires-Dist: amqp (==2.1.4)
Requires-Dist: vine (==1.1.3)
Requires-Dist: pytz (>=2016.7)
Requires-Dist: django-db-locking (>=2.0.0)
Requires-Dist: phonenumberslite (==7.3.2)
Requires-Dist: six (<2.0,>=1.11.0)
Requires-Dist: future (==0.16.0)
Requires-Dist: django-waffle (==0.16.0)
